phinitydata/__init__.py
phinitydata/client.py
phinitydata/connectors/__init__.py
phinitydata/connectors/base.py
phinitydata/connectors/chromadb.py
phinitydata/testset/__init__.py
phinitydata/testset/models.py
phinitydata/testset/rag_generator.py
phinitydata/testset/sft_generator.py
phinitydata-0.1.2.dist-info/METADATA
phinitydata-0.1.2.dist-info/WHEEL
phinitydata-0.1.2.dist-info/top_level.txt
phinitydata-0.1.2.dist-info/RECORD
